{
  "meta": {
    "build": {
      "build-date": "2023-12-01",
      "ci-build-number": "1.0.52",
      "ci-project": "mohicanlaw/law-xml",
      "codified-date": "2023-09-22",
      "platform": {
        "reproducible": "false",
        "version": "2.12.7"
      },
      "repositories": [
        {
          "commit": "f4a67d9b42adf2e6c135b2b041a5e96aa16f0032",
          "name": "mohicanlaw/law-xml"
        },
        {
          "commit": "854fb1e421dba7074aa1105a2f26a3cee12e196f",
          "name": "mohicanlaw/law-xml-codified-preview"
        }
      ]
    },
    "canonical-urls": {
      "html": "https://law.mohican.com",
      "html-bulk": "https://github.com/mohicanlaw/law-html",
      "law-git": "https://github.com/mohicanlaw/law.git",
      "static-assets": "https://github.com/mohicanlaw/law-static-assets",
      "xml-bulk": "https://github.com/mohicanlaw/law-xml"
    },
    "contact": {
      "email": "help@openlawlib.org"
    },
    "description": "",
    "history-start": "2021-01-28"
  }
}