{
  "meta": {
    "build": {
      "build-date": "2023-10-25",
      "ci-build-number": "1.0.50",
      "ci-project": "mohicanlaw/law-xml",
      "codified-date": "2023-09-22",
      "platform": {
        "reproducible": "false",
        "version": "2.12.7"
      },
      "repositories": [
        {
          "commit": "fc5294044e047beacf2b28c31bf7caa60e458e6f",
          "name": "mohicanlaw/law-xml"
        },
        {
          "commit": "4a36cde7270f3331f66cf1b5c77ee8aedc528c12",
          "name": "mohicanlaw/law-xml-codified-preview"
        }
      ]
    },
    "canonical-urls": {
      "html": "https://law.mohican.com",
      "html-bulk": "https://github.com/mohicanlaw/law-html",
      "law-git": "https://github.com/mohicanlaw/law.git",
      "static-assets": "https://github.com/mohicanlaw/law-static-assets",
      "xml-bulk": "https://github.com/mohicanlaw/law-xml"
    },
    "contact": {
      "email": "help@openlawlib.org"
    },
    "description": "",
    "history-start": "2021-01-28"
  }
}