{"t": "2023 SMTCA 1 Gregory Miller, et al. vs. Stockbridge-Munsee Community, et al.", "p": "/us/nsn/mohican/courts/appeals/opinions/2023/1", "et": "document", "sc": "Gregory Miller, et al. vs. Stockbridge-Munsee Community, et al., 2023 SMTCA 1, September 22, 2023.", "rd": "2023 SMTCA 1", "ei": "us/nsn/mohican/council/docs/opinion", "sp": "library|us/nsn/mohican/courts/appeals/opinions|2023|2023 SMTCA 1", "sd": true, "c": [{"t": "I. INTRODUCTION", "p": "/us/nsn/mohican/courts/appeals/opinions/2023/1#introduction", "et": "container", "sc": " I.", "cn": "INTRODUCTION", "rp": "INTRODUCTION", "sp": "library|us/nsn/mohican/courts/appeals/opinions|2023|2023 SMTCA 1|INTRODUCTION", "c": [{"t": "\u00b61", "p": "/us/nsn/mohican/courts/appeals/opinions/2023/1#paras/1", "et": "para", "sc": "I.\u00b61", "cn": "INTRODUCTION\u00b61", "rp": "INTRODUCTION|\u00b61", "x": "The Stockbridge-Munsee Community (\"Community\"), Stockbridge-Munsee Tribal C"}, {"t": "\u00b62", "p": "/us/nsn/mohican/courts/appeals/opinions/2023/1#paras/2", "et": "para", "sc": "I.\u00b62", "cn": "INTRODUCTION\u00b62", "rp": "INTRODUCTION|\u00b62", "x": "Based on this Court's opinion herein, the Tribal Court's order is AFFIRMED."}]}, {"t": "II. SUMMARY", "p": "/us/nsn/mohican/courts/appeals/opinions/2023/1#summary", "et": "container", "sc": " II.", "cn": "SUMMARY", "rp": "SUMMARY", "sp": "library|us/nsn/mohican/courts/appeals/opinions|2023|2023 SMTCA 1|SUMMARY", "c": [{"t": "\u00b63", "p": "/us/nsn/mohican/courts/appeals/opinions/2023/1#paras/3", "et": "para", "sc": "II.\u00b63", "cn": "SUMMARY\u00b63", "rp": "SUMMARY|\u00b63", "x": "On March 30, 2021, Petitioners-Appellees (hereinafter \"Appellees\") filed su"}, {"t": "\u00b64", "p": "/us/nsn/mohican/courts/appeals/opinions/2023/1#paras/4", "et": "para", "sc": "II.\u00b64", "cn": "SUMMARY\u00b64", "rp": "SUMMARY|\u00b64", "x": "Appellants filed their Motion to Dismiss and their Brief in support of the "}, {"t": "\u00b65", "p": "/us/nsn/mohican/courts/appeals/opinions/2023/1#paras/5", "et": "para", "sc": "II.\u00b65", "cn": "SUMMARY\u00b65", "rp": "SUMMARY|\u00b65", "x": "On July 5, 2022, the Tribal Council approved Res. No. 043-22 relating to ce"}]}, {"t": "III. APPELLANTS' ARGUMENT", "p": "/us/nsn/mohican/courts/appeals/opinions/2023/1#appellants-argument", "et": "container", "sc": " III.", "cn": "APPELLANTS' ARGUMENT", "rp": "APPELLANTS' ARGUMENT", "sp": "library|us/nsn/mohican/courts/appeals/opinions|2023|2023 SMTCA 1|APPELLANTS' ARGUMENT", "c": [{"t": "\u00b66", "p": "/us/nsn/mohican/courts/appeals/opinions/2023/1#paras/6", "et": "para", "sc": "III.\u00b66", "cn": "APPELLANTS' ARGUMENT\u00b66", "rp": "APPELLANTS' ARGUMENT|\u00b66", "x": "Appellants argue that due to the passage of Res. No. 043-22, Appellees' cla"}, {"t": "\u00b67", "p": "/us/nsn/mohican/courts/appeals/opinions/2023/1#paras/7", "et": "para", "sc": "III.\u00b67", "cn": "APPELLANTS' ARGUMENT\u00b67", "rp": "APPELLANTS' ARGUMENT|\u00b67", "x": "In furtherance of their position, Appellants assert the Appellee's sought r"}, {"t": "\u00b68", "p": "/us/nsn/mohican/courts/appeals/opinions/2023/1#paras/8", "et": "para", "sc": "III.\u00b68", "cn": "APPELLANTS' ARGUMENT\u00b68", "rp": "APPELLANTS' ARGUMENT|\u00b68", "x": "Appellees set forth the key elements of the mootness doctrine requiring tha"}, {"t": "\u00b69", "p": "/us/nsn/mohican/courts/appeals/opinions/2023/1#paras/9", "et": "para", "sc": "III.\u00b69", "cn": "APPELLANTS' ARGUMENT\u00b69", "rp": "APPELLANTS' ARGUMENT|\u00b69", "x": "Appellees also address the exceptions available to the mootness doctrine pr"}, {"t": "\u00b610", "p": "/us/nsn/mohican/courts/appeals/opinions/2023/1#paras/10", "et": "para", "sc": "III.\u00b610", "cn": "APPELLANTS' ARGUMENT\u00b610", "rp": "APPELLANTS' ARGUMENT|\u00b610", "x": "Appellants state the second exception occurs when the action is capable of "}, {"t": "\u00b611", "p": "/us/nsn/mohican/courts/appeals/opinions/2023/1#paras/11", "et": "para", "sc": "III.\u00b611", "cn": "APPELLANTS' ARGUMENT\u00b611", "rp": "APPELLANTS' ARGUMENT|\u00b611", "x": "Appellants argue that since Resolution NO. 043-22 was duly and constitution"}]}, {"t": "IV. APPELLEES' ARGUMENT", "p": "/us/nsn/mohican/courts/appeals/opinions/2023/1#appellees-argument", "et": "container", "sc": " IV.", "cn": "APPELLEES' ARGUMENT", "rp": "APPELLEES' ARGUMENT", "sp": "library|us/nsn/mohican/courts/appeals/opinions|2023|2023 SMTCA 1|APPELLEES' ARGUMENT", "c": [{"t": "\u00b612", "p": "/us/nsn/mohican/courts/appeals/opinions/2023/1#paras/12", "et": "para", "sc": "IV.\u00b612", "cn": "APPELLEES' ARGUMENT\u00b612", "rp": "APPELLEES' ARGUMENT|\u00b612", "x": "Appellees assert Defendants/Appellants claim that Resolution No. 043-22 moo"}, {"t": "\u00b613", "p": "/us/nsn/mohican/courts/appeals/opinions/2023/1#paras/13", "et": "para", "sc": "IV.\u00b613", "cn": "APPELLEES' ARGUMENT\u00b613", "rp": "APPELLEES' ARGUMENT|\u00b613", "c": [{"t": "1.", "p": "/us/nsn/mohican/courts/appeals/opinions/2023/1#paras/13/1.", "et": "para", "sc": "IV.\u00b6131.", "cn": "APPELLEES' ARGUMENT\u00b6131.", "rp": "APPELLEES' ARGUMENT|\u00b613|1.", "x": "\"Said resolution provided a historical summary behind the membership langua"}, {"t": "2.", "p": "/us/nsn/mohican/courts/appeals/opinions/2023/1#paras/13/2.", "et": "para", "sc": "IV.\u00b6132.", "cn": "APPELLEES' ARGUMENT\u00b6132.", "rp": "APPELLEES' ARGUMENT|\u00b613|2.", "x": "\"Said resolution] explained that the Community does not have a single base "}, {"t": "3.", "p": "/us/nsn/mohican/courts/appeals/opinions/2023/1#paras/13/3.", "et": "para", "sc": "IV.\u00b6133.", "cn": "APPELLEES' ARGUMENT\u00b6133.", "rp": "APPELLEES' ARGUMENT|\u00b613|3.", "x": "\"[Said resolution stated that] Tribal Council wants to 'strengthen the Trib"}, {"t": "4.", "p": "/us/nsn/mohican/courts/appeals/opinions/2023/1#paras/13/4.", "et": "para", "sc": "IV.\u00b6134.", "cn": "APPELLEES' ARGUMENT\u00b6134.", "rp": "APPELLEES' ARGUMENT|\u00b613|4.", "x": "\"Res. No. 043-22 ... reaffirm[ed] current Enrollment Department policies an"}, {"t": "5.", "p": "/us/nsn/mohican/courts/appeals/opinions/2023/1#paras/13/5.", "et": "para", "sc": "IV.\u00b6135.", "cn": "APPELLEES' ARGUMENT\u00b6135.", "rp": "APPELLEES' ARGUMENT|\u00b613|5.", "x": "\"Res. No. 043-22 ... approved a new enrollment application form.\" Id."}], "x": "Appellees assert Judge Redwine properly rejected Appellents' argument that "}, {"t": "\u00b614", "p": "/us/nsn/mohican/courts/appeals/opinions/2023/1#paras/14", "et": "para", "sc": "IV.\u00b614", "cn": "APPELLEES' ARGUMENT\u00b614", "rp": "APPELLEES' ARGUMENT|\u00b614", "x": "Appellees contend that Defendants/Appellants admit that none of these attri"}, {"t": "\u00b615", "p": "/us/nsn/mohican/courts/appeals/opinions/2023/1#paras/15", "et": "para", "sc": "IV.\u00b615", "cn": "APPELLEES' ARGUMENT\u00b615", "rp": "APPELLEES' ARGUMENT|\u00b615", "x": "Defendants/Appellants note this Court previously recognized the legality an"}, {"t": "\u00b616", "p": "/us/nsn/mohican/courts/appeals/opinions/2023/1#paras/16", "et": "para", "sc": "IV.\u00b616", "cn": "APPELLEES' ARGUMENT\u00b616", "rp": "APPELLEES' ARGUMENT|\u00b616", "x": "With respect to Defendants/Appellants specific argument that the Tribal Cou"}, {"t": "\u00b617", "p": "/us/nsn/mohican/courts/appeals/opinions/2023/1#paras/17", "et": "para", "sc": "IV.\u00b617", "cn": "APPELLEES' ARGUMENT\u00b617", "rp": "APPELLEES' ARGUMENT|\u00b617", "x": "Appellees further assert the Tribal Court fully considered all relevant inf"}, {"t": "\u00b618", "p": "/us/nsn/mohican/courts/appeals/opinions/2023/1#paras/18", "et": "para", "sc": "IV.\u00b618", "cn": "APPELLEES' ARGUMENT\u00b618", "rp": "APPELLEES' ARGUMENT|\u00b618", "x": "Appellees further contend that Judge Redwine has the authority to consider "}]}, {"t": "V. ABUSE OF DISCRETION STANDARD", "p": "/us/nsn/mohican/courts/appeals/opinions/2023/1#abuse-of-discretion-standard", "et": "container", "sc": " V.", "cn": "ABUSE OF DISCRETION STANDARD", "rp": "ABUSE OF DISCRETION STANDARD", "sp": "library|us/nsn/mohican/courts/appeals/opinions|2023|2023 SMTCA 1|ABUSE OF DISCRETION STANDARD", "c": [{"t": "\u00b619", "p": "/us/nsn/mohican/courts/appeals/opinions/2023/1#paras/19", "et": "para", "sc": "V.\u00b619", "cn": "ABUSE OF DISCRETION STANDARD\u00b619", "rp": "ABUSE OF DISCRETION STANDARD|\u00b619", "x": "The Stockbridge-Munsee Constitution, at Article III, \u00a7 41, states as follow"}, {"t": "\u00b620", "p": "/us/nsn/mohican/courts/appeals/opinions/2023/1#paras/20", "et": "para", "sc": "V.\u00b620", "cn": "ABUSE OF DISCRETION STANDARD\u00b620", "rp": "ABUSE OF DISCRETION STANDARD|\u00b620", "x": "The Stockbridge-Munsee Tribal Membership Ordinance, at \u00a7 Mem. 01.06, sets o"}, {"t": "\u00b621", "p": "/us/nsn/mohican/courts/appeals/opinions/2023/1#paras/21", "et": "para", "sc": "V.\u00b621", "cn": "ABUSE OF DISCRETION STANDARD\u00b621", "rp": "ABUSE OF DISCRETION STANDARD|\u00b621", "x": "Applying these rules, the Stockbridge-Munsee Tribal Council, on July 5, 202"}, {"t": "\u00b622", "p": "/us/nsn/mohican/courts/appeals/opinions/2023/1#paras/22", "et": "para", "sc": "V.\u00b622", "cn": "ABUSE OF DISCRETION STANDARD\u00b622", "rp": "ABUSE OF DISCRETION STANDARD|\u00b622", "x": "When reviewing the statutory exercise of discretion by a governmental body,"}, {"t": "\u00b623", "p": "/us/nsn/mohican/courts/appeals/opinions/2023/1#paras/23", "et": "para", "sc": "V.\u00b623", "cn": "ABUSE OF DISCRETION STANDARD\u00b623", "rp": "ABUSE OF DISCRETION STANDARD|\u00b623", "x": "When a government body can legitimately answer a question \"Yes\" or \"No.\" or"}, {"t": "\u00b624", "p": "/us/nsn/mohican/courts/appeals/opinions/2023/1#paras/24", "et": "para", "sc": "V.\u00b624", "cn": "ABUSE OF DISCRETION STANDARD\u00b624", "rp": "ABUSE OF DISCRETION STANDARD|\u00b624", "x": "The case at hand tracks the logic of both Tribal and Wisconsin definitions "}, {"t": "\u00b625", "p": "/us/nsn/mohican/courts/appeals/opinions/2023/1#paras/25", "et": "para", "sc": "V.\u00b625", "cn": "ABUSE OF DISCRETION STANDARD\u00b625", "rp": "ABUSE OF DISCRETION STANDARD|\u00b625", "x": "When reviewing the statutory exercise of discretion by a governmental body,"}, {"t": "\u00b626", "p": "/us/nsn/mohican/courts/appeals/opinions/2023/1#paras/26", "et": "para", "sc": "V.\u00b626", "cn": "ABUSE OF DISCRETION STANDARD\u00b626", "rp": "ABUSE OF DISCRETION STANDARD|\u00b626", "x": "When a government body can legitimately answer a question \"Yes\" or \"No.\" or"}, {"t": "\u00b627", "p": "/us/nsn/mohican/courts/appeals/opinions/2023/1#paras/27", "et": "para", "sc": "V.\u00b627", "cn": "ABUSE OF DISCRETION STANDARD\u00b627", "rp": "ABUSE OF DISCRETION STANDARD|\u00b627", "x": "The case at hand tracks the logic of both Tribal and Wisconsin definitions "}, {"t": "\u00b628", "p": "/us/nsn/mohican/courts/appeals/opinions/2023/1#paras/28", "et": "para", "sc": "V.\u00b628", "cn": "ABUSE OF DISCRETION STANDARD\u00b628", "rp": "ABUSE OF DISCRETION STANDARD|\u00b628", "x": "In the case at hand, the matter is remanded for a trial on the merits where"}]}, {"t": "VI. CONCLUSION", "p": "/us/nsn/mohican/courts/appeals/opinions/2023/1#conclusion", "et": "container", "sc": " VI.", "cn": "CONCLUSION", "rp": "CONCLUSION", "sp": "library|us/nsn/mohican/courts/appeals/opinions|2023|2023 SMTCA 1|CONCLUSION", "c": [{"t": "\u00b629", "p": "/us/nsn/mohican/courts/appeals/opinions/2023/1#paras/29", "et": "para", "sc": "VI.\u00b629", "cn": "CONCLUSION\u00b629", "rp": "CONCLUSION|\u00b629", "x": "Here, this Court finds that issues presented by Appellees are sufficient to"}, {"t": "\u00b630", "p": "/us/nsn/mohican/courts/appeals/opinions/2023/1#paras/30", "et": "para", "sc": "VI.\u00b630", "cn": "CONCLUSION\u00b630", "rp": "CONCLUSION|\u00b630", "x": "The Court therefore orders that the Tribal Court's Second Motion to Dismiss"}, {"t": "\u00b631", "p": "/us/nsn/mohican/courts/appeals/opinions/2023/1#paras/31", "et": "para", "sc": "VI.\u00b631", "cn": "CONCLUSION\u00b631", "rp": "CONCLUSION|\u00b631", "x": "If the Tribal Court finds that the Tribal Council did act outside its offic"}]}]}