{"t": "Case No. 3-AP-2013-CV-0002. Robert Miller III vs. Bart D.Schultz.", "p": "/us/nsn/mohican/courts/appeals/opinions/2014/2014 SMTCA 1", "et": "document", "sc": "2014 SMTCA 1", "sp": "library|us/nsn/mohican/council/opinions|2014|2014 SMTCA 1", "sd": true, "c": [{"t": "None", "p": "/us/nsn/mohican/courts/appeals/opinions/2014/2014 SMTCA 1#introduction", "et": "container", "sc": "None", "sp": "library|us/nsn/mohican/council/opinions|2014|2014 SMTCA 1|"}, {"t": "None", "p": "/us/nsn/mohican/courts/appeals/opinions/2014/2014 SMTCA 1#statement-of-the-case", "et": "container", "sc": "None", "sp": "library|us/nsn/mohican/council/opinions|2014|2014 SMTCA 1|"}, {"t": "None", "p": "/us/nsn/mohican/courts/appeals/opinions/2014/2014 SMTCA 1#discussion", "et": "container", "sc": "None", "sp": "library|us/nsn/mohican/council/opinions|2014|2014 SMTCA 1|", "c": [{"t": "None", "p": "/us/nsn/mohican/courts/appeals/opinions/2014/2014 SMTCA 1#discussionjurisdiction", "et": "container", "sc": "None", "sp": "library|us/nsn/mohican/council/opinions|2014|2014 SMTCA 1||"}, {"t": "None", "p": "/us/nsn/mohican/courts/appeals/opinions/2014/2014 SMTCA 1#discussiondue-process", "et": "container", "sc": "None", "sp": "library|us/nsn/mohican/council/opinions|2014|2014 SMTCA 1||"}, {"t": "None", "p": "/us/nsn/mohican/courts/appeals/opinions/2014/2014 SMTCA 1#discussionstatute-of-limitations", "et": "container", "sc": "None", "sp": "library|us/nsn/mohican/council/opinions|2014|2014 SMTCA 1||"}, {"t": "None", "p": "/us/nsn/mohican/courts/appeals/opinions/2014/2014 SMTCA 1#discussiongrant-of-summary-judgment", "et": "container", "sc": "None", "sp": "library|us/nsn/mohican/council/opinions|2014|2014 SMTCA 1||"}]}, {"t": "None", "p": "/us/nsn/mohican/courts/appeals/opinions/2014/2014 SMTCA 1#conclusion", "et": "container", "sc": "None", "sp": "library|us/nsn/mohican/council/opinions|2014|2014 SMTCA 1|"}]}