{
  "meta": {
    "build": {
      "build-date": "2023-10-24",
      "codified-date": "2023-09-22",
      "platform": {
        "reproducible": "false",
        "version": "2.13.0"
      },
      "repositories": [
        {
          "commit": "44e0644c335bb1e301fa48c58cfdb14b37953213",
          "name": "mohicanlaw/law-xml"
        },
        {
          "commit": "ef9395ed89dd9621cbb3839d0feb1285b59c4cfb",
          "name": "mohicanlaw/law-xml-codified-preview"
        }
      ]
    },
    "canonical-urls": {
      "html": "https://law.mohican.com",
      "html-bulk": "https://github.com/mohicanlaw/law-html",
      "law-git": "https://github.com/mohicanlaw/law.git",
      "static-assets": "https://github.com/mohicanlaw/law-static-assets",
      "xml-bulk": "https://github.com/mohicanlaw/law-xml"
    },
    "contact": {
      "email": "help@openlawlib.org"
    },
    "description": "",
    "history-start": "2021-01-28"
  }
}