{"t": "Case No. AP-2011-02. Lynne  Miller vs. Judge Robert Miller Jr.", "p": "/us/nsn/mohican/courts/appeals/opinions/2011/2011 SMTCA 1", "et": "document", "sc": "2011 SMTCA 1", "sp": "library|us/nsn/mohican/council/opinions|2011|2011 SMTCA 1", "sd": true, "c": [{"t": "None", "p": "/us/nsn/mohican/courts/appeals/opinions/2011/2011 SMTCA 1#introduction", "et": "container", "sc": "None", "sp": "library|us/nsn/mohican/council/opinions|2011|2011 SMTCA 1|"}, {"t": "None", "p": "/us/nsn/mohican/courts/appeals/opinions/2011/2011 SMTCA 1#background", "et": "container", "sc": "None", "sp": "library|us/nsn/mohican/council/opinions|2011|2011 SMTCA 1|"}, {"t": "None", "p": "/us/nsn/mohican/courts/appeals/opinions/2011/2011 SMTCA 1#standard-of-review", "et": "container", "sc": "None", "sp": "library|us/nsn/mohican/council/opinions|2011|2011 SMTCA 1|"}, {"t": "None", "p": "/us/nsn/mohican/courts/appeals/opinions/2011/2011 SMTCA 1#analysis", "et": "container", "sc": "None", "sp": "library|us/nsn/mohican/council/opinions|2011|2011 SMTCA 1|"}]}